HISTORY.md
LICENSE
MANIFEST.in
README.MD
README.md
setup.cfg
setup.py
demo/demo.txt
docs/API.md
kutool/__init__.py
kutool/__version__.py
kutool/demo.py
kutool.egg-info/PKG-INFO
kutool.egg-info/SOURCES.txt
kutool.egg-info/dependency_links.txt
kutool.egg-info/top_level.txt
tests/tests.txt